mypandas/app.py
mycalc_sechanjang-0.0.2.dist-info/METADATA
mycalc_sechanjang-0.0.2.dist-info/WHEEL
mycalc_sechanjang-0.0.2.dist-info/top_level.txt
mycalc_sechanjang-0.0.2.dist-info/RECORD
