Metadata-Version: 2.1
Name: mycalc-sechanjang
Version: 0.0.2
Author: sechanjang
Classifier: Programming Language :: Python :: 3
Classifier: License :: OSI Approved :: MIT License
Classifier: Operating System :: OS Independent
Requires-Dist: numpy
Requires-Dist: pandas
